ddecon/__init__.py
ddecon/async_econ.py
ddecon/econ.py
ddecon/exceptions.py
ddecon-0.2.2.dist-info/licenses/LICENSE
ddecon-0.2.2.dist-info/METADATA
ddecon-0.2.2.dist-info/WHEEL
ddecon-0.2.2.dist-info/top_level.txt
ddecon-0.2.2.dist-info/RECORD
