Metadata-Version: 2.4
Name: ddecon
Version: 0.2.2
Summary: DDnet econ
Home-page: https://github.com/ByFox213/ddecon
Author: ByFox
Project-URL: Github, https://github.com/ByFox213/ddecon
Classifier: Programming Language :: Python :: 3
Classifier: License :: OSI Approved :: MIT License
Classifier: Operating System :: OS Independent
Requires-Python: >=3.10
License-File: LICENSE
Dynamic: author
Dynamic: classifier
Dynamic: description
Dynamic: description-content-type
Dynamic: home-page
Dynamic: license-file
Dynamic: project-url
Dynamic: requires-python
Dynamic: summary
